tradelab/__init__.py
tradelab/candles/__init__.py
tradelab/candles/heikinashi/__init__.py
tradelab/candles/heikinashi/heikinashi.c
tradelab/candles/heikinashi/heikinashi.cp313-win_amd64.pyd
tradelab/candles/heikinashi/heikinashi.pyx
tradelab/candles/heikinashi/wrapper.py
tradelab/candles/renko/__init__.py
tradelab/candles/renko/renko.c
tradelab/candles/renko/renko.cp313-win_amd64.pyd
tradelab/candles/renko/renko.pyx
tradelab/candles/renko/wrapper.py
tradelab/indicators/__init__.py
tradelab/indicators/adx/__init__.py
tradelab/indicators/adx/adx.c
tradelab/indicators/adx/adx.cp313-win_amd64.pyd
tradelab/indicators/adx/adx.pyx
tradelab/indicators/adx/wrapper.py
tradelab/indicators/donchian_channels/__init__.py
tradelab/indicators/donchian_channels/donchian_channels.c
tradelab/indicators/donchian_channels/donchian_channels.cp313-win_amd64.pyd
tradelab/indicators/donchian_channels/donchian_channels.pyx
tradelab/indicators/donchian_channels/wrapper.py
tradelab/indicators/ema/__init__.py
tradelab/indicators/ema/ema.c
tradelab/indicators/ema/ema.cp313-win_amd64.pyd
tradelab/indicators/ema/ema.pyx
tradelab/indicators/ema/wrapper.py
tradelab/indicators/macd/__init__.py
tradelab/indicators/macd/macd.c
tradelab/indicators/macd/macd.cp313-win_amd64.pyd
tradelab/indicators/macd/macd.pyx
tradelab/indicators/macd/wrapper.py
tradelab/indicators/normalized_t3/__init__.py
tradelab/indicators/normalized_t3/normalized_t3.c
tradelab/indicators/normalized_t3/normalized_t3.cp313-win_amd64.pyd
tradelab/indicators/normalized_t3/normalized_t3.pyx
tradelab/indicators/normalized_t3/wrapper.py
tradelab/indicators/relative_strength/__init__.py
tradelab/indicators/relative_strength/relative_strength.c
tradelab/indicators/relative_strength/relative_strength.cp313-win_amd64.pyd
tradelab/indicators/relative_strength/relative_strength.pyx
tradelab/indicators/relative_strength/wrapper.py
tradelab/indicators/rsi/__init__.py
tradelab/indicators/rsi/rsi.c
tradelab/indicators/rsi/rsi.cp313-win_amd64.pyd
tradelab-0.2.5.dist-info/licenses/LICENSE
tradelab-0.2.5.dist-info/METADATA
tradelab-0.2.5.dist-info/WHEEL
tradelab-0.2.5.dist-info/top_level.txt
tradelab-0.2.5.dist-info/RECORD
