Metadata-Version: 2.4
Name: tradelab
Version: 0.2.5
Summary: A simple and powerful Python package for algorithmic trading and technical analysis. Calculate technical indicators and analyze market data with ease.
Author-email: Husain Chhil <hychhil@gmail.com>
Project-URL: Homepage, https://github.com/husainchhil/TradeLab
Requires-Python: >=3.11
License-File: LICENSE
Requires-Dist: numpy<2.3.0,>=2.0.0
Requires-Dist: pandas<=2.2.3
Dynamic: license-file
